{
  "source_image": "data\\train\\images\\002.jpg",
  "line_index": 1,
  "bbox": {
    "left": 0,
    "top": 122,
    "right": 49,
    "bottom": 168
  },
  "baseline": [
    [
      3,
      150
    ],
    [
      37,
      150
    ]
  ],
  "boundary": [
    [
      3,
      150
    ],
    [
      3,
      156
    ],
    [
      37,
      154
    ],
    [
      37,
      150
    ],
    [
      36,
      134
    ],
    [
      3,
      141
    ],
    [
      3,
      150
    ]
  ],
  "id": "_35060428-73c1-4c2d-b23f-65ba161a0602"
}
