{
  "source_image": "data\\train\\images\\005.jpg",
  "line_index": 11,
  "bbox": {
    "left": 226,
    "top": 741,
    "right": 255,
    "bottom": 787
  },
  "baseline": [
    [
      238,
      768
    ],
    [
      243,
      768
    ]
  ],
  "boundary": [
    [
      238,
      768
    ],
    [
      238,
      775
    ],
    [
      243,
      775
    ],
    [
      243,
      768
    ],
    [
      241,
      753
    ],
    [
      238,
      754
    ],
    [
      238,
      768
    ]
  ],
  "id": "_172563d9-4133-406a-a428-5c0584eb3c27"
}
