{
  "source_image": "data\\train\\images\\020.jpg",
  "line_index": 6,
  "bbox": {
    "left": 357,
    "top": 415,
    "right": 391,
    "bottom": 474
  },
  "baseline": [
    [
      371,
      454
    ],
    [
      379,
      454
    ]
  ],
  "boundary": [
    [
      371,
      454
    ],
    [
      371,
      460
    ],
    [
      378,
      462
    ],
    [
      379,
      454
    ],
    [
      376,
      427
    ],
    [
      369,
      428
    ],
    [
      371,
      454
    ]
  ],
  "id": "_9c2fff8d-79f8-4671-91a8-1f51aeaade25"
}
