{
  "source_image": "data\\train\\images\\037.jpg",
  "line_index": 11,
  "bbox": {
    "left": 412,
    "top": 613,
    "right": 445,
    "bottom": 655
  },
  "baseline": [
    [
      424,
      635
    ],
    [
      433,
      635
    ]
  ],
  "boundary": [
    [
      424,
      635
    ],
    [
      424,
      643
    ],
    [
      432,
      643
    ],
    [
      433,
      635
    ],
    [
      432,
      625
    ],
    [
      424,
      625
    ],
    [
      424,
      635
    ]
  ],
  "id": "_fd0a99e2-229a-4521-b62c-71693d9922f7"
}
