{
  "source_image": "data\\train\\images\\039.jpg",
  "line_index": 3,
  "bbox": {
    "left": 269,
    "top": 420,
    "right": 301,
    "bottom": 484
  },
  "baseline": [
    [
      281,
      457
    ],
    [
      289,
      457
    ]
  ],
  "boundary": [
    [
      281,
      471
    ],
    [
      288,
      472
    ],
    [
      289,
      457
    ],
    [
      289,
      435
    ],
    [
      282,
      432
    ],
    [
      281,
      457
    ],
    [
      281,
      471
    ]
  ],
  "id": "_fe2da45b-9340-4e23-92a8-1bfa63dd948c"
}
