{
  "source_image": "data\\train\\images\\045.jpg",
  "line_index": 9,
  "bbox": {
    "left": 262,
    "top": 477,
    "right": 296,
    "bottom": 531
  },
  "baseline": [
    [
      276,
      511
    ],
    [
      284,
      510
    ]
  ],
  "boundary": [
    [
      276,
      511
    ],
    [
      277,
      519
    ],
    [
      284,
      516
    ],
    [
      284,
      510
    ],
    [
      282,
      490
    ],
    [
      274,
      489
    ],
    [
      276,
      511
    ]
  ],
  "id": "_a043e377-a1f6-4daf-8dbb-60289a5ea2c2"
}
