{
  "source_image": "data\\train\\images\\066.jpg",
  "line_index": 9,
  "bbox": {
    "left": 185,
    "top": 490,
    "right": 266,
    "bottom": 568
  },
  "baseline": [
    [
      198,
      525
    ],
    [
      254,
      523
    ]
  ],
  "boundary": [
    [
      198,
      552
    ],
    [
      216,
      556
    ],
    [
      216,
      556
    ],
    [
      217,
      556
    ],
    [
      217,
      556
    ],
    [
      217,
      555
    ],
    [
      240,
      533
    ],
    [
      254,
      533
    ],
    [
      254,
      523
    ],
    [
      253,
      509
    ],
    [
      241,
      502
    ],
    [
      240,
      502
    ],
    [
      240,
      502
    ],
    [
      239,
      502
    ],
    [
      238,
      502
    ],
    [
      225,
      511
    ],
    [
      211,
      511
    ],
    [
      197,
      504
    ],
    [
      198,
      525
    ],
    [
      198,
      552
    ]
  ],
  "id": "_f81f533d-800c-4e92-91dc-2170b0dd743b"
}
