{
  "source_image": "data\\train\\images\\078.jpg",
  "line_index": 6,
  "bbox": {
    "left": 287,
    "top": 891,
    "right": 329,
    "bottom": 936
  },
  "baseline": [
    [
      301,
      913
    ],
    [
      316,
      917
    ]
  ],
  "boundary": [
    [
      315,
      906
    ],
    [
      309,
      904
    ],
    [
      303,
      903
    ],
    [
      301,
      913
    ],
    [
      299,
      919
    ],
    [
      313,
      924
    ],
    [
      316,
      917
    ],
    [
      317,
      906
    ],
    [
      315,
      906
    ]
  ],
  "id": "_0d0b8af2-dea6-41e9-a80b-3e689df47064"
}
