{
  "source_image": "data\\train\\images\\086.jpg",
  "line_index": 13,
  "bbox": {
    "left": 445,
    "top": 613,
    "right": 499,
    "bottom": 652
  },
  "baseline": [
    [
      476,
      627
    ],
    [
      477,
      639
    ]
  ],
  "boundary": [
    [
      476,
      627
    ],
    [
      457,
      628
    ],
    [
      462,
      640
    ],
    [
      477,
      639
    ],
    [
      484,
      638
    ],
    [
      487,
      625
    ],
    [
      476,
      627
    ]
  ],
  "id": "_4d2b5b8e-9afb-489b-978d-751a9c01eb21"
}
