{
  "source_image": "data\\train\\images\\099.jpg",
  "line_index": 5,
  "bbox": {
    "left": 500,
    "top": 631,
    "right": 563,
    "bottom": 678
  },
  "baseline": [
    [
      542,
      666
    ],
    [
      543,
      645
    ]
  ],
  "boundary": [
    [
      542,
      666
    ],
    [
      551,
      666
    ],
    [
      551,
      645
    ],
    [
      543,
      645
    ],
    [
      512,
      643
    ],
    [
      520,
      665
    ],
    [
      542,
      666
    ]
  ],
  "id": "_ff8abd29-ad10-4c49-9c5f-c1c752adb83e"
}
