{
  "source_image": "data\\train\\images\\104.jpg",
  "line_index": 22,
  "bbox": {
    "left": 483,
    "top": 764,
    "right": 514,
    "bottom": 803
  },
  "baseline": [
    [
      495,
      784
    ],
    [
      502,
      784
    ]
  ],
  "boundary": [
    [
      495,
      784
    ],
    [
      495,
      791
    ],
    [
      502,
      791
    ],
    [
      502,
      784
    ],
    [
      502,
      777
    ],
    [
      496,
      776
    ],
    [
      495,
      784
    ]
  ],
  "id": "_bf92c934-f678-4de3-93cb-efb302566e9e"
}
