{
  "source_image": "data\\train\\images\\111.jpg",
  "line_index": 19,
  "bbox": {
    "left": 150,
    "top": 621,
    "right": 220,
    "bottom": 667
  },
  "baseline": [
    [
      163,
      648
    ],
    [
      208,
      646
    ]
  ],
  "boundary": [
    [
      163,
      648
    ],
    [
      163,
      652
    ],
    [
      184,
      655
    ],
    [
      185,
      655
    ],
    [
      208,
      650
    ],
    [
      208,
      646
    ],
    [
      207,
      633
    ],
    [
      178,
      639
    ],
    [
      162,
      638
    ],
    [
      163,
      648
    ]
  ],
  "id": "_c71e1caa-58e8-49b4-a84b-92d11225b060"
}
