{
  "source_image": "data\\train\\images\\128.jpg",
  "line_index": 2,
  "bbox": {
    "left": 151,
    "top": 417,
    "right": 201,
    "bottom": 457
  },
  "baseline": [
    [
      178,
      429
    ],
    [
      178,
      445
    ]
  ],
  "boundary": [
    [
      178,
      429
    ],
    [
      163,
      429
    ],
    [
      163,
      444
    ],
    [
      178,
      445
    ],
    [
      189,
      444
    ],
    [
      188,
      429
    ],
    [
      178,
      429
    ]
  ],
  "id": "_45eaaa8b-ae1f-40d6-8a37-08197b607ebd"
}
