{
  "source_image": "data\\train\\images\\131.jpg",
  "line_index": 10,
  "bbox": {
    "left": 244,
    "top": 738,
    "right": 312,
    "bottom": 791
  },
  "baseline": [
    [
      288,
      750
    ],
    [
      289,
      778
    ]
  ],
  "boundary": [
    [
      288,
      750
    ],
    [
      256,
      751
    ],
    [
      260,
      761
    ],
    [
      257,
      771
    ],
    [
      257,
      771
    ],
    [
      257,
      772
    ],
    [
      257,
      772
    ],
    [
      257,
      773
    ],
    [
      261,
      779
    ],
    [
      289,
      778
    ],
    [
      300,
      777
    ],
    [
      299,
      750
    ],
    [
      288,
      750
    ]
  ],
  "id": "_8e1b780a-3024-4aa7-a763-5c5631facf8c"
}
