{
  "source_image": "data\\train\\images\\138.jpg",
  "line_index": 13,
  "bbox": {
    "left": 330,
    "top": 724,
    "right": 376,
    "bottom": 755
  },
  "baseline": [
    [
      351,
      741
    ],
    [
      351,
      738
    ]
  ],
  "boundary": [
    [
      351,
      738
    ],
    [
      342,
      736
    ],
    [
      342,
      739
    ],
    [
      351,
      741
    ],
    [
      364,
      743
    ],
    [
      364,
      741
    ],
    [
      351,
      738
    ]
  ],
  "id": "_0e8667de-ee0c-4c75-8fe6-36712a3a1a00"
}
