{
  "source_image": "data\\train\\images\\140.jpg",
  "line_index": 25,
  "bbox": {
    "left": 265,
    "top": 995,
    "right": 304,
    "bottom": 1026
  },
  "baseline": [
    [
      285,
      1007
    ],
    [
      285,
      1014
    ]
  ],
  "boundary": [
    [
      285,
      1007
    ],
    [
      277,
      1007
    ],
    [
      277,
      1014
    ],
    [
      285,
      1014
    ],
    [
      292,
      1014
    ],
    [
      292,
      1007
    ],
    [
      285,
      1007
    ]
  ],
  "id": "_dcfcf1d7-8024-4100-bba1-8695b5009972"
}
