{
  "source_image": "data\\train\\images\\140.jpg",
  "line_index": 8,
  "bbox": {
    "left": 60,
    "top": 528,
    "right": 115,
    "bottom": 603
  },
  "baseline": [
    [
      72,
      582
    ],
    [
      103,
      582
    ]
  ],
  "boundary": [
    [
      72,
      582
    ],
    [
      72,
      586
    ],
    [
      78,
      590
    ],
    [
      78,
      590
    ],
    [
      79,
      590
    ],
    [
      79,
      591
    ],
    [
      95,
      591
    ],
    [
      95,
      590
    ],
    [
      96,
      590
    ],
    [
      103,
      585
    ],
    [
      103,
      582
    ],
    [
      103,
      549
    ],
    [
      82,
      540
    ],
    [
      81,
      540
    ],
    [
      81,
      540
    ],
    [
      80,
      540
    ],
    [
      79,
      540
    ],
    [
      79,
      541
    ],
    [
      72,
      548
    ],
    [
      72,
      582
    ]
  ],
  "id": "_a5e3de40-595a-4b1d-9678-31ce4a848bbe"
}
