{
  "source_image": "data\\train\\images\\144.jpg",
  "line_index": 22,
  "bbox": {
    "left": 401,
    "top": 798,
    "right": 430,
    "bottom": 862
  },
  "baseline": [
    [
      413,
      846
    ],
    [
      418,
      846
    ]
  ],
  "boundary": [
    [
      413,
      850
    ],
    [
      418,
      850
    ],
    [
      418,
      846
    ],
    [
      418,
      812
    ],
    [
      414,
      810
    ],
    [
      413,
      846
    ],
    [
      413,
      850
    ]
  ],
  "id": "_3f8c02a5-aedf-43cb-9533-4d2c69aaebf4"
}
