{
  "source_image": "data\\train\\images\\154.jpg",
  "line_index": 2,
  "bbox": {
    "left": 66,
    "top": 43,
    "right": 1246,
    "bottom": 153
  },
  "baseline": [
    [
      79,
      130
    ],
    [
      386,
      118
    ],
    [
      592,
      112
    ],
    [
      1234,
      107
    ]
  ],
  "boundary": [
    [
      79,
      130
    ],
    [
      80,
      141
    ],
    [
      187,
      139
    ],
    [
      188,
      139
    ],
    [
      224,
      130
    ],
    [
      265,
      132
    ],
    [
      265,
      132
    ],
    [
      266,
      132
    ],
    [
      279,
      128
    ],
    [
      294,
      130
    ],
    [
      294,
      130
    ],
    [
      333,
      126
    ],
    [
      344,
      129
    ],
    [
      345,
      129
    ],
    [
      345,
      129
    ],
    [
      346,
      129
    ],
    [
      361,
      125
    ],
    [
      378,
      127
    ],
    [
      378,
      127
    ],
    [
      414,
      123
    ],
    [
      427,
      126
    ],
    [
      428,
      126
    ],
    [
      429,
      126
    ],
    [
      473,
      121
    ],
    [
      489,
      124
    ],
    [
      489,
      124
    ],
    [
      490,
      124
    ],
    [
      502,
      120
    ],
    [
      545,
      122
    ],
    [
      546,
      122
    ],
    [
      546,
      122
    ],
    [
      557,
      118
    ],
    [
      574,
      122
    ],
    [
      575,
      122
    ],
    [
      576,
      122
    ],
    [
      588,
      118
    ],
    [
      606,
      120
    ],
    [
      606,
      120
    ],
    [
      646,
      117
    ],
    [
      659,
      120
    ],
    [
      660,
      120
    ],
    [
      660,
      120
    ],
    [
      661,
      120
    ],
    [
      674,
      116
    ],
    [
      693,
      119
    ],
    [
      694,
      119
    ],
    [
      694,
      119
    ],
    [
      705,
      115
    ],
    [
      748,
      118
    ],
    [
      748,
      118
    ],
    [
      749,
      118
    ],
    [
      762,
      115
    ],
    [
      774,
      118
    ],
    [
      775,
      118
    ],
    [
      775,
      118
    ],
    [
      791,
      115
    ],
    [
      810,
      118
    ],
    [
      810,
      118
    ],
    [
      811,
      118
    ],
    [
      822,
      114
    ],
    [
      867,
      117
    ],
    [
      867,
      117
    ],
    [
      868,
      117
    ],
    [
      880,
      114
    ],
    [
      893,
      117
    ],
    [
      894,
      117
    ],
    [
      894,
      117
    ],
    [
      940,
      113
    ],
    [
      958,
      116
    ],
    [
      958,
      116
    ],
    [
      999,
      112
    ],
    [
      1042,
      116
    ],
    [
      1042,
      116
    ],
    [
      1043,
      116
    ],
    [
      1058,
      111
    ],
    [
      1072,
      115
    ],
    [
      1073,
      115
    ],
    [
      1074,
      115
    ],
    [
      1074,
      115
    ],
    [
      1087,
      112
    ],
    [
      1131,
      114
    ],
    [
      1132,
      114
    ],
    [
      1132,
      114
    ],
    [
      1146,
      111
    ],
    [
      1164,
      115
    ],
    [
      1165,
      115
    ],
    [
      1200,
      109
    ],
    [
      1221,
      114
    ],
    [
      1221,
      114
    ],
    [
      1234,
      112
    ],
    [
      1234,
      107
    ],
    [
      1233,
      70
    ],
    [
      1094,
      70
    ],
    [
      1077,
      65
    ],
    [
      1077,
      65
    ],
    [
      1076,
      65
    ],
    [
      1075,
      65
    ],
    [
      1063,
      68
    ],
    [
      1019,
      63
    ],
    [
      1018,
      63
    ],
    [
      1018,
      63
    ],
    [
      1007,
      66
    ],
    [
      990,
      61
    ],
    [
      990,
      61
    ],
    [
      989,
      61
    ],
    [
      974,
      64
    ],
    [
      932,
      58
    ],
    [
      931,
      58
    ],
    [
      919,
      61
    ],
    [
      904,
      57
    ],
    [
      903,
      57
    ],
    [
      903,
      57
    ],
    [
      902,
      57
    ],
    [
      891,
      60
    ],
    [
      875,
      55
    ],
    [
      874,
      55
    ],
    [
      874,
      55
    ],
    [
      820,
      55
    ],
    [
      575,
      60
    ],
    [
      574,
      60
    ],
    [
      496,
      80
    ],
    [
      481,
      77
    ],
    [
      481,
      77
    ],
    [
      480,
      77
    ],
    [
      467,
      81
    ],
    [
      429,
      78
    ],
    [
      429,
      78
    ],
    [
      388,
      83
    ],
    [
      306,
      83
    ],
    [
      291,
      79
    ],
    [
      290,
      79
    ],
    [
      196,
      83
    ],
    [
      183,
      80
    ],
    [
      183,
      80
    ],
    [
      182,
      80
    ],
    [
      181,
      80
    ],
    [
      171,
      83
    ],
    [
      156,
      79
    ],
    [
      156,
      79
    ],
    [
      155,
      79
    ],
    [
      154,
      79
    ],
    [
      132,
      87
    ],
    [
      78,
      87
    ],
    [
      79,
      130
    ]
  ],
  "id": "_3acf888c-d33c-4682-8596-db36a1d4baa2"
}
