{
  "source_image": "data\\train\\images\\160.jpg",
  "line_index": 12,
  "bbox": {
    "left": 630,
    "top": 521,
    "right": 673,
    "bottom": 627
  },
  "baseline": [
    [
      652,
      553
    ],
    [
      659,
      554
    ]
  ],
  "boundary": [
    [
      642,
      611
    ],
    [
      646,
      615
    ],
    [
      659,
      554
    ],
    [
      661,
      537
    ],
    [
      656,
      533
    ],
    [
      652,
      553
    ],
    [
      642,
      611
    ]
  ],
  "id": "_99b74935-72e5-4498-832f-3f332bf62360"
}
