{
  "source_image": "data\\train\\images\\162.jpg",
  "line_index": 2,
  "bbox": {
    "left": 257,
    "top": 354,
    "right": 296,
    "bottom": 448
  },
  "baseline": [
    [
      277,
      366
    ],
    [
      277,
      436
    ]
  ],
  "boundary": [
    [
      277,
      366
    ],
    [
      269,
      366
    ],
    [
      271,
      436
    ],
    [
      277,
      436
    ],
    [
      284,
      435
    ],
    [
      283,
      366
    ],
    [
      277,
      366
    ]
  ],
  "id": "_496e0922-e374-4854-a868-2426688bda6f"
}
