{
  "source_image": "data\\train\\images\\172.jpg",
  "line_index": 3,
  "bbox": {
    "left": 663,
    "top": 416,
    "right": 710,
    "bottom": 447
  },
  "baseline": [
    [
      688,
      430
    ],
    [
      688,
      433
    ]
  ],
  "boundary": [
    [
      688,
      430
    ],
    [
      675,
      433
    ],
    [
      676,
      435
    ],
    [
      688,
      433
    ],
    [
      698,
      431
    ],
    [
      698,
      428
    ],
    [
      688,
      430
    ]
  ],
  "id": "_b94fde0f-affa-44b0-be6b-856a84c9f376"
}
