{
  "source_image": "data\\train\\images\\177.jpg",
  "line_index": 17,
  "bbox": {
    "left": 664,
    "top": 529,
    "right": 750,
    "bottom": 574
  },
  "baseline": [
    [
      726,
      541
    ],
    [
      726,
      562
    ]
  ],
  "boundary": [
    [
      738,
      562
    ],
    [
      738,
      541
    ],
    [
      726,
      541
    ],
    [
      676,
      541
    ],
    [
      677,
      561
    ],
    [
      726,
      562
    ],
    [
      738,
      562
    ]
  ],
  "id": "_352b9899-ba34-4744-91b1-2e0545563e5c"
}
