{
  "source_image": "data\\train\\images\\178.jpg",
  "line_index": 42,
  "bbox": {
    "left": 840,
    "top": 182,
    "right": 871,
    "bottom": 231
  },
  "baseline": [
    [
      856,
      215
    ],
    [
      859,
      214
    ]
  ],
  "boundary": [
    [
      856,
      215
    ],
    [
      856,
      219
    ],
    [
      859,
      219
    ],
    [
      859,
      214
    ],
    [
      854,
      194
    ],
    [
      852,
      195
    ],
    [
      856,
      215
    ]
  ],
  "id": "_64f5d97a-85d2-47f4-8378-d4f9df17cc59"
}
