{
  "source_image": "data\\train\\images\\191.jpg",
  "line_index": 9,
  "bbox": {
    "left": 388,
    "top": 319,
    "right": 418,
    "bottom": 367
  },
  "baseline": [
    [
      400,
      341
    ],
    [
      406,
      341
    ]
  ],
  "boundary": [
    [
      406,
      341
    ],
    [
      406,
      333
    ],
    [
      401,
      331
    ],
    [
      400,
      341
    ],
    [
      401,
      355
    ],
    [
      406,
      352
    ],
    [
      406,
      341
    ]
  ],
  "id": "_78ba3c79-e360-4be1-b905-c3535ecd695d"
}
