{
  "source_image": "data\\train\\images\\191.jpg",
  "line_index": 10,
  "bbox": {
    "left": 415,
    "top": 850,
    "right": 456,
    "bottom": 887
  },
  "baseline": [
    [
      427,
      869
    ],
    [
      444,
      869
    ]
  ],
  "boundary": [
    [
      427,
      869
    ],
    [
      427,
      875
    ],
    [
      444,
      873
    ],
    [
      444,
      869
    ],
    [
      444,
      862
    ],
    [
      427,
      862
    ],
    [
      427,
      869
    ]
  ],
  "id": "_99fef5c5-808f-415d-a60a-0d14a07a000f"
}
