{
  "source_image": "data\\train\\images\\204.jpg",
  "line_index": 13,
  "bbox": {
    "left": 278,
    "top": 553,
    "right": 332,
    "bottom": 588
  },
  "baseline": [
    [
      310,
      567
    ],
    [
      310,
      576
    ]
  ],
  "boundary": [
    [
      310,
      567
    ],
    [
      294,
      567
    ],
    [
      290,
      575
    ],
    [
      310,
      576
    ],
    [
      320,
      574
    ],
    [
      319,
      565
    ],
    [
      310,
      567
    ]
  ],
  "id": "_e83fbf24-47ff-41eb-a4b6-9b4b34a26f00"
}
