{
  "source_image": "data\\train\\images\\209.jpg",
  "line_index": 4,
  "bbox": {
    "left": 127,
    "top": 0,
    "right": 917,
    "bottom": 66
  },
  "baseline": [
    [
      140,
      43
    ],
    [
      190,
      43
    ],
    [
      372,
      33
    ],
    [
      905,
      13
    ]
  ],
  "boundary": [
    [
      901,
      0
    ],
    [
      894,
      0
    ],
    [
      888,
      0
    ],
    [
      882,
      0
    ],
    [
      876,
      0
    ],
    [
      870,
      0
    ],
    [
      864,
      0
    ],
    [
      858,
      0
    ],
    [
      852,
      0
    ],
    [
      850,
      0
    ],
    [
      139,
      24
    ],
    [
      140,
      43
    ],
    [
      141,
      54
    ],
    [
      158,
      50
    ],
    [
      171,
      52
    ],
    [
      171,
      52
    ],
    [
      172,
      52
    ],
    [
      189,
      45
    ],
    [
      225,
      46
    ],
    [
      226,
      46
    ],
    [
      226,
      46
    ],
    [
      236,
      43
    ],
    [
      261,
      49
    ],
    [
      262,
      49
    ],
    [
      292,
      45
    ],
    [
      300,
      48
    ],
    [
      301,
      48
    ],
    [
      301,
      48
    ],
    [
      360,
      46
    ],
    [
      415,
      35
    ],
    [
      431,
      38
    ],
    [
      432,
      38
    ],
    [
      432,
      38
    ],
    [
      443,
      34
    ],
    [
      459,
      39
    ],
    [
      459,
      39
    ],
    [
      460,
      39
    ],
    [
      460,
      39
    ],
    [
      474,
      32
    ],
    [
      487,
      32
    ],
    [
      555,
      38
    ],
    [
      556,
      38
    ],
    [
      556,
      38
    ],
    [
      566,
      34
    ],
    [
      596,
      37
    ],
    [
      597,
      37
    ],
    [
      597,
      37
    ],
    [
      613,
      30
    ],
    [
      627,
      33
    ],
    [
      627,
      33
    ],
    [
      628,
      33
    ],
    [
      645,
      25
    ],
    [
      694,
      24
    ],
    [
      705,
      27
    ],
    [
      706,
      27
    ],
    [
      706,
      27
    ],
    [
      738,
      22
    ],
    [
      780,
      21
    ],
    [
      788,
      24
    ],
    [
      789,
      24
    ],
    [
      789,
      24
    ],
    [
      809,
      20
    ],
    [
      834,
      27
    ],
    [
      835,
      27
    ],
    [
      835,
      27
    ],
    [
      836,
      27
    ],
    [
      853,
      23
    ],
    [
      862,
      26
    ],
    [
      863,
      26
    ],
    [
      864,
      26
    ],
    [
      904,
      25
    ],
    [
      905,
      13
    ],
    [
      903,
      0
    ],
    [
      901,
      0
    ]
  ],
  "id": "_fba6bcb4-cc4a-48b3-bdec-a1fe8d639ea5"
}
